dbt/adapters/ibmdb2/__init__.py
dbt/adapters/ibmdb2/__version__.py
dbt/adapters/ibmdb2/column.py
dbt/adapters/ibmdb2/connections.py
dbt/adapters/ibmdb2/impl.py
dbt/adapters/ibmdb2/relation.py
dbt/include/ibmdb2/__init__.py
dbt/include/ibmdb2/dbt_project.yml
dbt/include/ibmdb2/macros/adapters.sql
dbt/include/ibmdb2/macros/apply_grants.sql
dbt/include/ibmdb2/macros/catalog.sql
dbt/include/ibmdb2/macros/materializations/incremental/incremental.sql
dbt/include/ibmdb2/macros/materializations/seeds/helpers.sql
dbt/include/ibmdb2/macros/materializations/table/table.sql
dbt/include/ibmdb2/macros/materializations/view/view.sql
dbt/include/ibmdb2/macros/utils/datatypes.sql
dbt/include/ibmdb2/macros/utils/dateadd.sql
dbt/include/ibmdb2/macros/utils/datediff.sql
dbt/include/ibmdb2/macros/utils/hash.sql
dbt/include/ibmdb2/macros/utils/last_day.sql
dbt/include/ibmdb2/macros/utils/position.sql
dbt/include/ibmdb2/macros/utils/split_part.sql
dbt/include/ibmdb2/macros/utils/timestamps.sql
dbt/include/ibmdb2/sample_profiles.yml
dbt_ibmdb2-1.8.0.dist-info/LICENSE
dbt_ibmdb2-1.8.0.dist-info/METADATA
dbt_ibmdb2-1.8.0.dist-info/WHEEL
dbt_ibmdb2-1.8.0.dist-info/RECORD
