Metadata-Version: 2.1
Name: dbt-ibmdb2
Version: 1.8.0
Summary: The db2 adapter plugin for dbt (data build tool)
Home-page: https://github.com/aurany/dbt-ibmdb2
License: Apache Software License 2.0
Keywords: dbt,ibm,db2,data,engineering
Author: aurany
Author-email: rasmus.nyberg@gmail.com
Requires-Python: >=3.8
Classifier: License :: Other/Proprietary License
Classifier: Programming Language :: Python :: 3
Classifier: Programming Language :: Python :: 3.8
Classifier: Programming Language :: Python :: 3.9
Classifier: Programming Language :: Python :: 3.10
Classifier: Programming Language :: Python :: 3.11
Classifier: Programming Language :: Python :: 3.12
Requires-Dist: dbt-core (>=1.8.0)
Requires-Dist: ibm-db (>=3.1.0,<4.0.0)
Project-URL: Repository, https://github.com/aurany/dbt-ibmdb2
